Metadata-Version: 2.4
Name: sauce-api-mcp-fastmcp
Version: 1.0.4
Summary: MCP server for Sauce Labs API
Author-email: Marcus Merrell <marcus.merrell@saucelabs.com>
Project-URL: Homepage, https://github.com/fastmcp-me/sauce-api-mcp#readme
Project-URL: Repository, https://github.com/fastmcp-me/sauce-api-mcp.git
Project-URL: Issues, https://github.com/fastmcp-me/sauce-api-mcp/issues
Classifier: Development Status :: 5 - Production/Stable
Classifier: Intended Audience :: Developers
Classifier: License :: OSI Approved :: Apache Software License
Classifier: Programming Language :: Python :: 3
Classifier: Programming Language :: Python :: 3.9
Classifier: Programming Language :: Python :: 3.10
Classifier: Programming Language :: Python :: 3.11
Classifier: Programming Language :: Python :: 3.12
Requires-Python: >=3.10
License-File: LICENSE
Requires-Dist: httpx
Requires-Dist: pydantic
Requires-Dist: mcp
Provides-Extra: test
Requires-Dist: pytest; extra == "test"
Requires-Dist: pytest-asyncio; extra == "test"
Dynamic: license-file
